{
    "id": "d43807ff-628d-4687-9d04-3cd7329707a0",
    "link": "https://ballchasing.com/api/replays/d43807ff-628d-4687-9d04-3cd7329707a0",
    "created": "2025-01-31T18:35:36.487475Z",
    "uploader": {
        "steam_id": "76561199225615730",
        "name": "RLCS Referee",
        "profile_url": "https://steamcommunity.com/profiles/76561199225615730/",
        "avatar": "https://avatars.steamstatic.com/f84a836e794362eb3c53d50ac7893daa04c53c3d.jpg"
    },
    "status": "ok",
    "rocket_league_id": "1155BF9442B86215BA632D9F3256E905",
    "match_guid": "AFD66F7211EFDFFDF0EC4FA26EE3B5AE",
    "title": "2025-01-31.19.10 Mat. Private Win",
    "map_code": "stadium_p",
    "match_type": "Private",
    "team_size": 3,
    "playlist_id": "private",
    "duration": 372,
    "overtime": false,
    "season": 17,
    "season_type": "free2play",
    "date": "2025-01-31T19:10:50+01:00",
    "date_has_timezone": true,
    "visibility": "public",
    "groups": [
        {
            "id": "asc-vs-m8-rklwxvqmmm",
            "name": "ASC vs M8",
            "link": "https://ballchasing.com/api/groups/asc-vs-m8-rklwxvqmmm"
        }
    ],
    "blue": {
        "color": "blue",
        "name": "ASCEND",
        "players": [
            {
                "start_time": 0,
                "end_time": 372.65393,
                "name": "Nico",
                "id": {
                    "platform": "steam",
                    "id": "76561198818204178"
                },
                "mvp": true,
                "car_id": 4284,
                "car_name": "Fennec",
                "camera": {
                    "fov": 110,
                    "height": 100,
                    "pitch": -3,
                    "distance": 260,
                    "stiffness": 0.5,
                    "swivel_speed": 6.5,
                    "transition_speed": 1.9
                },
                "steering_sensitivity": 2.5,
                "stats": {
                    "core": {
                        "shots": 3,
                        "shots_against": 13,
                        "goals": 2,
                        "goals_against": 2,
                        "saves": 5,
                        "assists": 0,
                        "score": 706,
                        "mvp": true,
                        "shooting_percentage": 66.666664
                    },
                    "boost": {
                        "bpm": 389,
                        "bcpm": 425.48993,
                        "avg_amount": 53.58,
                        "amount_collected": 2515,
                        "amount_stolen": 386,
                        "amount_collected_big": 2046,
                        "amount_stolen_big": 232,
                        "amount_collected_small": 469,
                        "amount_stolen_small": 154,
                        "count_collected_big": 30,
                        "count_stolen_big": 3,
                        "count_collected_small": 42,
                        "count_stolen_small": 14,
                        "amount_overfill": 784,
                        "amount_overfill_stolen": 70,
                        "amount_used_while_supersonic": 520,
                        "time_zero_boost": 28.82,
                        "percent_zero_boost": 8.126322,
                        "time_full_boost": 70.19,
                        "percent_full_boost": 19.791344,
                        "time_boost_0_25": 106.91,
                        "time_boost_25_50": 69.33,
                        "time_boost_50_75": 75.66,
                        "time_boost_75_100": 116.01,
                        "percent_boost_0_25": 29.058737,
                        "percent_boost_25_50": 18.844282,
                        "percent_boost_50_75": 20.564814,
                        "percent_boost_75_100": 31.532167
                    },
                    "movement": {
                        "avg_speed": 1541,
                        "total_distance": 539463,
                        "time_supersonic_speed": 72.69,
                        "time_boost_speed": 132.69,
                        "time_slow_speed": 165.84,
                        "time_ground": 210.27,
                        "time_low_air": 145.09,
                        "time_high_air": 15.86,
                        "time_powerslide": 5.64,
                        "count_powerslide": 44,
                        "avg_powerslide_duration": 0.13,
                        "avg_speed_percentage": 67,
                        "percent_slow_speed": 44.674316,
                        "percent_boost_speed": 35.7443,
                        "percent_supersonic_speed": 19.58138,
                        "percent_ground": 56.642967,
                        "percent_low_air": 39.084644,
                        "percent_high_air": 4.2723994
                    },
                    "positioning": {
                        "avg_distance_to_ball": 2600,
                        "avg_distance_to_ball_possession": 2522,
                        "avg_distance_to_ball_no_possession": 2672,
                        "avg_distance_to_mates": 3461,
                        "time_defensive_third": 197,
                        "time_neutral_third": 123.45,
                        "time_offensive_third": 50.77,
                        "time_defensive_half": 269.43,
                        "time_offensive_half": 101.79,
                        "time_behind_ball": 274.34,
                        "time_infront_ball": 96.88,
                        "time_most_back": 120.4,
                        "time_most_forward": 122.8,
                        "goals_against_while_last_defender": 1,
                        "time_closest_to_ball": 115.6,
                        "time_farthest_from_ball": 118.4,
                        "percent_defensive_third": 53.06826,
                        "percent_offensive_third": 13.676526,
                        "percent_neutral_third": 33.25521,
                        "percent_defensive_half": 72.579605,
                        "percent_offensive_half": 27.420397,
                        "percent_behind_ball": 73.90227,
                        "percent_infront_ball": 26.097733,
                        "percent_most_back": 33.948963,
                        "percent_most_forward": 34.625687,
                        "percent_closest_to_ball": 32.595516,
                        "percent_farthest_from_ball": 33.38503
                    },
                    "demo": {
                        "inflicted": 1,
                        "taken": 1
                    }
                }
            },
            {
                "start_time": 0,
                "end_time": 372.65393,
                "name": "GiuK",
                "id": {
                    "platform": "steam",
                    "id": "76561198811209484"
                },
                "car_id": 4284,
                "car_name": "Fennec",
                "camera": {
                    "fov": 110,
                    "height": 100,
                    "pitch": -3,
                    "distance": 270,
                    "stiffness": 0.6,
                    "swivel_speed": 7,
                    "transition_speed": 2
                },
                "steering_sensitivity": 1.6,
                "stats": {
                    "core": {
                        "shots": 2,
                        "shots_against": 13,
                        "goals": 1,
                        "goals_against": 2,
                        "saves": 2,
                        "assists": 0,
                        "score": 414,
                        "mvp": false,
                        "shooting_percentage": 50
                    },
                    "boost": {
                        "bpm": 377,
                        "bcpm": 408.0643,
                        "avg_amount": 49.95,
                        "amount_collected": 2412,
                        "amount_stolen": 331,
                        "amount_collected_big": 1787,
                        "amount_stolen_big": 243,
                        "amount_collected_small": 625,
                        "amount_stolen_small": 88,
                        "count_collected_big": 22,
                        "count_stolen_big": 3,
                        "count_collected_small": 57,
                        "count_stolen_small": 8,
                        "amount_overfill": 347,
                        "amount_overfill_stolen": 56,
                        "amount_used_while_supersonic": 375,
                        "time_zero_boost": 44.36,
                        "percent_zero_boost": 12.508107,
                        "time_full_boost": 31.55,
                        "percent_full_boost": 8.896095,
                        "time_boost_0_25": 128.87,
                        "time_boost_25_50": 69.98,
                        "time_boost_50_75": 84.62,
                        "time_boost_75_100": 76.56,
                        "percent_boost_0_25": 35.79424,
                        "percent_boost_25_50": 19.437271,
                        "percent_boost_50_75": 23.503597,
                        "percent_boost_75_100": 21.264894
                    },
                    "movement": {
                        "avg_speed": 1533,
                        "total_distance": 528393,
                        "time_supersonic_speed": 64.44,
                        "time_boost_speed": 134.26,
                        "time_slow_speed": 170.22,
                        "time_ground": 205.56,
                        "time_low_air": 139.21,
                        "time_high_air": 24.15,
                        "time_powerslide": 5.33,
                        "count_powerslide": 51,
                        "avg_powerslide_duration": 0.1,
                        "avg_speed_percentage": 66.652176,
                        "percent_slow_speed": 46.140087,
                        "percent_boost_speed": 36.39271,
                        "percent_supersonic_speed": 17.467203,
                        "percent_ground": 55.719395,
                        "percent_low_air": 37.73447,
                        "percent_high_air": 6.5461345
                    },
                    "positioning": {
                        "avg_distance_to_ball": 2768,
                        "avg_distance_to_ball_possession": 2681,
                        "avg_distance_to_ball_no_possession": 2833,
                        "avg_distance_to_mates": 3452,
                        "time_defensive_third": 220.33,
                        "time_neutral_third": 104.49,
                        "time_offensive_third": 44.09,
                        "time_defensive_half": 277.83,
                        "time_offensive_half": 91.09,
                        "time_behind_ball": 283.96,
                        "time_infront_ball": 84.95,
                        "time_most_back": 152.5,
                        "time_most_forward": 87.2,
                        "goals_against_while_last_defender": 1,
                        "time_closest_to_ball": 97.1,
                        "time_farthest_from_ball": 139.4,
                        "percent_defensive_third": 59.724594,
                        "percent_offensive_third": 11.951425,
                        "percent_neutral_third": 28.32398,
                        "percent_defensive_half": 75.309006,
                        "percent_offensive_half": 24.69099,
                        "percent_behind_ball": 76.97271,
                        "percent_infront_ball": 23.027298,
                        "percent_most_back": 43.00014,
                        "percent_most_forward": 24.587622,
                        "percent_closest_to_ball": 27.379107,
                        "percent_farthest_from_ball": 39.306355
                    },
                    "demo": {
                        "inflicted": 1,
                        "taken": 1
                    }
                }
            },
            {
                "start_time": 0,
                "end_time": 372.65393,
                "name": "Mat.",
                "id": {
                    "platform": "steam",
                    "id": "76561198151775989"
                },
                "car_id": 4284,
                "car_name": "Fennec",
                "camera": {
                    "fov": 110,
                    "height": 100,
                    "pitch": -4,
                    "distance": 270,
                    "stiffness": 0.35,
                    "swivel_speed": 4.5,
                    "transition_speed": 1.3
                },
                "steering_sensitivity": 1.67,
                "stats": {
                    "core": {
                        "shots": 1,
                        "shots_against": 13,
                        "goals": 0,
                        "goals_against": 2,
                        "saves": 3,
                        "assists": 2,
                        "score": 410,
                        "mvp": false,
                        "shooting_percentage": 0
                    },
                    "boost": {
                        "bpm": 387,
                        "bcpm": 400.28198,
                        "avg_amount": 40.27,
                        "amount_collected": 2366,
                        "amount_stolen": 357,
                        "amount_collected_big": 1319,
                        "amount_stolen_big": 100,
                        "amount_collected_small": 1047,
                        "amount_stolen_small": 257,
                        "count_collected_big": 15,
                        "count_stolen_big": 1,
                        "count_collected_small": 84,
                        "count_stolen_small": 23,
                        "amount_overfill": 81,
                        "amount_overfill_stolen": 9,
                        "amount_used_while_supersonic": 170,
                        "time_zero_boost": 78.47,
                        "percent_zero_boost": 22.12604,
                        "time_full_boost": 11.81,
                        "percent_full_boost": 3.3300438,
                        "time_boost_0_25": 186.07,
                        "time_boost_25_50": 72.56,
                        "time_boost_50_75": 41.39,
                        "time_boost_75_100": 65.5,
                        "percent_boost_0_25": 50.905556,
                        "percent_boost_25_50": 19.85117,
                        "percent_boost_50_75": 11.323593,
                        "percent_boost_75_100": 17.919676
                    },
                    "movement": {
                        "avg_speed": 1562,
                        "total_distance": 546168,
                        "time_supersonic_speed": 42.53,
                        "time_boost_speed": 176.36,
                        "time_slow_speed": 153.25,
                        "time_ground": 168.28,
                        "time_low_air": 182.14,
                        "time_high_air": 21.72,
                        "time_powerslide": 5.34,
                        "count_powerslide": 59,
                        "avg_powerslide_duration": 0.09,
                        "avg_speed_percentage": 67.91304,
                        "percent_slow_speed": 41.18074,
                        "percent_boost_speed": 47.39077,
                        "percent_supersonic_speed": 11.428495,
                        "percent_ground": 45.219543,
                        "percent_low_air": 48.943947,
                        "percent_high_air": 5.8365135
                    },
                    "positioning": {
                        "avg_distance_to_ball": 2513,
                        "avg_distance_to_ball_possession": 2588,
                        "avg_distance_to_ball_no_possession": 2429,
                        "avg_distance_to_mates": 3393,
                        "time_defensive_third": 181.12,
                        "time_neutral_third": 115.64,
                        "time_offensive_third": 75.38,
                        "time_defensive_half": 241.26,
                        "time_offensive_half": 130.88,
                        "time_behind_ball": 241.53,
                        "time_infront_ball": 130.6,
                        "time_most_back": 85.3,
                        "time_most_forward": 142.2,
                        "time_closest_to_ball": 141.4,
                        "time_farthest_from_ball": 98.5,
                        "percent_defensive_third": 48.669853,
                        "percent_offensive_third": 20.255816,
                        "percent_neutral_third": 31.074326,
                        "percent_defensive_half": 64.83044,
                        "percent_offensive_half": 35.16956,
                        "percent_behind_ball": 64.90474,
                        "percent_infront_ball": 35.095264,
                        "percent_most_back": 24.051882,
                        "percent_most_forward": 40.09587,
                        "percent_closest_to_ball": 39.870293,
                        "percent_farthest_from_ball": 27.773863
                    },
                    "demo": {
                        "inflicted": 0,
                        "taken": 0
                    }
                }
            }
        ],
        "stats": {
            "ball": {
                "possession_time": 149.15,
                "time_in_side": 194.93
            },
            "core": {
                "shots": 6,
                "shots_against": 13,
                "goals": 3,
                "goals_against": 2,
                "saves": 10,
                "assists": 2,
                "score": 1530,
                "shooting_percentage": 50
            },
            "boost": {
                "bpm": 1153,
                "bcpm": 1233.8362,
                "avg_amount": 143.8,
                "amount_collected": 7293,
                "amount_stolen": 1074,
                "amount_collected_big": 5152,
                "amount_stolen_big": 575,
                "amount_collected_small": 2141,
                "amount_stolen_small": 499,
                "count_collected_big": 67,
                "count_stolen_big": 7,
                "count_collected_small": 183,
                "count_stolen_small": 45,
                "amount_overfill": 1212,
                "amount_overfill_stolen": 135,
                "amount_used_while_supersonic": 1065,
                "time_zero_boost": 151.65,
                "time_full_boost": 113.55,
                "time_boost_0_25": 421.85,
                "time_boost_25_50": 211.87,
                "time_boost_50_75": 201.67,
                "time_boost_75_100": 258.07
            },
            "movement": {
                "total_distance": 1614024,
                "time_supersonic_speed": 179.66,
                "time_boost_speed": 443.31,
                "time_slow_speed": 489.31,
                "time_ground": 584.11,
                "time_low_air": 466.44,
                "time_high_air": 61.729996,
                "time_powerslide": 16.31,
                "count_powerslide": 154
            },
            "positioning": {
                "time_defensive_third": 598.45,
                "time_neutral_third": 343.58002,
                "time_offensive_third": 170.23999,
                "time_defensive_half": 788.52,
                "time_offensive_half": 323.76,
                "time_behind_ball": 799.82996,
                "time_infront_ball": 312.43
            },
            "demo": {
                "inflicted": 2,
                "taken": 2
            }
        }
    },
    "orange": {
        "color": "orange",
        "name": "GENTLE MATES",
        "players": [
            {
                "start_time": 0,
                "end_time": 372.65393,
                "name": "juicy",
                "id": {
                    "platform": "steam",
                    "id": "76561199013030566"
                },
                "car_id": 4284,
                "car_name": "Fennec",
                "camera": {
                    "fov": 110,
                    "height": 90,
                    "pitch": -4,
                    "distance": 270,
                    "stiffness": 0.45,
                    "swivel_speed": 7,
                    "transition_speed": 1.2
                },
                "steering_sensitivity": 1.4,
                "stats": {
                    "core": {
                        "shots": 5,
                        "shots_against": 6,
                        "goals": 1,
                        "goals_against": 3,
                        "saves": 1,
                        "assists": 0,
                        "score": 376,
                        "mvp": false,
                        "shooting_percentage": 20
                    },
                    "boost": {
                        "bpm": 389,
                        "bcpm": 395.03735,
                        "avg_amount": 41.92,
                        "amount_collected": 2335,
                        "amount_stolen": 498,
                        "amount_collected_big": 1307,
                        "amount_stolen_big": 91,
                        "amount_collected_small": 1028,
                        "amount_stolen_small": 407,
                        "count_collected_big": 16,
                        "count_stolen_big": 1,
                        "count_collected_small": 91,
                        "count_stolen_small": 37,
                        "amount_overfill": 278,
                        "amount_overfill_stolen": 19,
                        "amount_used_while_supersonic": 215,
                        "time_zero_boost": 43.49,
                        "percent_zero_boost": 12.2627945,
                        "time_full_boost": 20.39,
                        "percent_full_boost": 5.7493305,
                        "time_boost_0_25": 159.96,
                        "time_boost_25_50": 101.95,
                        "time_boost_50_75": 35.38,
                        "time_boost_75_100": 59.53,
                        "percent_boost_0_25": 44.829327,
                        "percent_boost_25_50": 28.571829,
                        "percent_boost_50_75": 9.915363,
                        "percent_boost_75_100": 16.683481
                    },
                    "movement": {
                        "avg_speed": 1619,
                        "total_distance": 560230,
                        "time_supersonic_speed": 65.49,
                        "time_boost_speed": 157.48,
                        "time_slow_speed": 145.89,
                        "time_ground": 214.05,
                        "time_low_air": 134.09,
                        "time_high_air": 20.72,
                        "time_powerslide": 6.75,
                        "count_powerslide": 72,
                        "avg_powerslide_duration": 0.09,
                        "avg_speed_percentage": 70.391304,
                        "percent_slow_speed": 39.551594,
                        "percent_boost_speed": 42.693707,
                        "percent_supersonic_speed": 17.754704,
                        "percent_ground": 58.030144,
                        "percent_low_air": 36.352543,
                        "percent_high_air": 5.617307
                    },
                    "positioning": {
                        "avg_distance_to_ball": 2463,
                        "avg_distance_to_ball_possession": 2390,
                        "avg_distance_to_ball_no_possession": 2540,
                        "avg_distance_to_mates": 3126,
                        "time_defensive_third": 160.36,
                        "time_neutral_third": 114.01,
                        "time_offensive_third": 94.5,
                        "time_defensive_half": 207.13,
                        "time_offensive_half": 161.74,
                        "time_behind_ball": 286.24,
                        "time_infront_ball": 82.63,
                        "time_most_back": 140.9,
                        "time_most_forward": 99.7,
                        "goals_against_while_last_defender": 1,
                        "time_closest_to_ball": 111.2,
                        "time_farthest_from_ball": 116.7,
                        "percent_defensive_third": 43.473312,
                        "percent_offensive_third": 25.618782,
                        "percent_neutral_third": 30.907907,
                        "percent_defensive_half": 56.152576,
                        "percent_offensive_half": 43.847427,
                        "percent_behind_ball": 77.59915,
                        "percent_infront_ball": 22.400846,
                        "percent_most_back": 39.72931,
                        "percent_most_forward": 28.112225,
                        "percent_closest_to_ball": 31.354856,
                        "percent_farthest_from_ball": 32.90568
                    },
                    "demo": {
                        "inflicted": 0,
                        "taken": 1
                    }
                }
            },
            {
                "start_time": 0,
                "end_time": 372.65393,
                "name": "radosin75",
                "id": {
                    "platform": "steam",
                    "id": "76561199009010912"
                },
                "car_id": 4284,
                "car_name": "Fennec",
                "camera": {
                    "fov": 109,
                    "height": 90,
                    "pitch": -5,
                    "distance": 270,
                    "stiffness": 0.35,
                    "swivel_speed": 4.2,
                    "transition_speed": 1.5
                },
                "steering_sensitivity": 1.9,
                "stats": {
                    "core": {
                        "shots": 4,
                        "shots_against": 6,
                        "goals": 1,
                        "goals_against": 3,
                        "saves": 0,
                        "assists": 1,
                        "score": 296,
                        "mvp": false,
                        "shooting_percentage": 25
                    },
                    "boost": {
                        "bpm": 413,
                        "bcpm": 410.77118,
                        "avg_amount": 44.52,
                        "amount_collected": 2428,
                        "amount_stolen": 506,
                        "amount_collected_big": 1553,
                        "amount_stolen_big": 127,
                        "amount_collected_small": 875,
                        "amount_stolen_small": 379,
                        "count_collected_big": 19,
                        "count_stolen_big": 2,
                        "count_collected_small": 78,
                        "count_stolen_small": 34,
                        "amount_overfill": 361,
                        "amount_overfill_stolen": 82,
                        "amount_used_while_supersonic": 464,
                        "time_zero_boost": 55.07,
                        "percent_zero_boost": 15.527986,
                        "time_full_boost": 31.43,
                        "percent_full_boost": 8.862259,
                        "time_boost_0_25": 182.32,
                        "time_boost_25_50": 59.41,
                        "time_boost_50_75": 75.11,
                        "time_boost_75_100": 49.37,
                        "percent_boost_0_25": 49.78564,
                        "percent_boost_25_50": 16.22293,
                        "percent_boost_50_75": 20.510088,
                        "percent_boost_75_100": 13.481335
                    },
                    "movement": {
                        "avg_speed": 1573,
                        "total_distance": 549856,
                        "time_supersonic_speed": 58.56,
                        "time_boost_speed": 153.49,
                        "time_slow_speed": 159.38,
                        "time_ground": 209,
                        "time_low_air": 151.02,
                        "time_high_air": 11.41,
                        "time_powerslide": 5.71,
                        "count_powerslide": 45,
                        "avg_powerslide_duration": 0.13,
                        "avg_speed_percentage": 68.391304,
                        "percent_slow_speed": 42.909836,
                        "percent_boost_speed": 41.324074,
                        "percent_supersonic_speed": 15.766093,
                        "percent_ground": 56.269012,
                        "percent_low_air": 40.659073,
                        "percent_high_air": 3.071911
                    },
                    "positioning": {
                        "avg_distance_to_ball": 2555,
                        "avg_distance_to_ball_possession": 2403,
                        "avg_distance_to_ball_no_possession": 2695,
                        "avg_distance_to_mates": 3206,
                        "time_defensive_third": 147.44,
                        "time_neutral_third": 120.85,
                        "time_offensive_third": 103.13,
                        "time_defensive_half": 208.06,
                        "time_offensive_half": 163.37,
                        "time_behind_ball": 276.86,
                        "time_infront_ball": 94.57,
                        "time_most_back": 134.1,
                        "time_most_forward": 116.7,
                        "goals_against_while_last_defender": 1,
                        "time_closest_to_ball": 115.6,
                        "time_farthest_from_ball": 133.4,
                        "percent_defensive_third": 39.6963,
                        "percent_offensive_third": 27.766409,
                        "percent_neutral_third": 32.53729,
                        "percent_defensive_half": 56.015938,
                        "percent_offensive_half": 43.984062,
                        "percent_behind_ball": 74.53894,
                        "percent_infront_ball": 25.461056,
                        "percent_most_back": 37.81193,
                        "percent_most_forward": 32.90568,
                        "percent_closest_to_ball": 32.595516,
                        "percent_farthest_from_ball": 37.614548
                    },
                    "demo": {
                        "inflicted": 2,
                        "taken": 0
                    }
                }
            },
            {
                "start_time": 0,
                "end_time": 372.65393,
                "name": "Seikoo",
                "id": {
                    "platform": "steam",
                    "id": "76561199013057612"
                },
                "car_id": 4284,
                "car_name": "Fennec",
                "camera": {
                    "fov": 110,
                    "height": 100,
                    "pitch": -3,
                    "distance": 240,
                    "stiffness": 0.3,
                    "swivel_speed": 4.4,
                    "transition_speed": 1.4
                },
                "steering_sensitivity": 1.8,
                "stats": {
                    "core": {
                        "shots": 4,
                        "shots_against": 6,
                        "goals": 0,
                        "goals_against": 3,
                        "saves": 0,
                        "assists": 1,
                        "score": 274,
                        "mvp": false,
                        "shooting_percentage": 0
                    },
                    "boost": {
                        "bpm": 443,
                        "bcpm": 457.80347,
                        "avg_amount": 49.19,
                        "amount_collected": 2706,
                        "amount_stolen": 1110,
                        "amount_collected_big": 1896,
                        "amount_stolen_big": 810,
                        "amount_collected_small": 810,
                        "amount_stolen_small": 300,
                        "count_collected_big": 26,
                        "count_stolen_big": 10,
                        "count_collected_small": 66,
                        "count_stolen_small": 27,
                        "amount_overfill": 612,
                        "amount_overfill_stolen": 188,
                        "amount_used_while_supersonic": 479,
                        "time_zero_boost": 39.89,
                        "percent_zero_boost": 11.247709,
                        "time_full_boost": 68.29,
                        "percent_full_boost": 19.255604,
                        "time_boost_0_25": 105.4,
                        "time_boost_25_50": 89.11,
                        "time_boost_50_75": 69.25,
                        "time_boost_75_100": 103.23,
                        "percent_boost_0_25": 28.720127,
                        "percent_boost_25_50": 24.281315,
                        "percent_boost_50_75": 18.869722,
                        "percent_boost_75_100": 28.12883
                    },
                    "movement": {
                        "avg_speed": 1588,
                        "total_distance": 550161,
                        "time_supersonic_speed": 53.14,
                        "time_boost_speed": 161.42,
                        "time_slow_speed": 154.43,
                        "time_ground": 194.22,
                        "time_low_air": 141.91,
                        "time_high_air": 32.85,
                        "time_powerslide": 7.79,
                        "count_powerslide": 67,
                        "avg_powerslide_duration": 0.12,
                        "avg_speed_percentage": 69.04348,
                        "percent_slow_speed": 41.85208,
                        "percent_boost_speed": 43.746445,
                        "percent_supersonic_speed": 14.401475,
                        "percent_ground": 52.636997,
                        "percent_low_air": 38.46008,
                        "percent_high_air": 8.902921
                    },
                    "positioning": {
                        "avg_distance_to_ball": 2458,
                        "avg_distance_to_ball_possession": 2289,
                        "avg_distance_to_ball_no_possession": 2636,
                        "avg_distance_to_mates": 3263,
                        "time_defensive_third": 127.22,
                        "time_neutral_third": 121.86,
                        "time_offensive_third": 119.91,
                        "time_defensive_half": 190.85,
                        "time_offensive_half": 178.13,
                        "time_behind_ball": 256.78,
                        "time_infront_ball": 112.21,
                        "time_most_back": 83,
                        "time_most_forward": 135.7,
                        "goals_against_while_last_defender": 1,
                        "time_closest_to_ball": 125,
                        "time_farthest_from_ball": 105.7,
                        "percent_defensive_third": 34.4779,
                        "percent_offensive_third": 32.496815,
                        "percent_neutral_third": 33.025288,
                        "percent_defensive_half": 51.72367,
                        "percent_offensive_half": 48.27633,
                        "percent_behind_ball": 69.589966,
                        "percent_infront_ball": 30.41004,
                        "percent_most_back": 23.403357,
                        "percent_most_forward": 38.263077,
                        "percent_closest_to_ball": 35.246017,
                        "percent_farthest_from_ball": 29.804033
                    },
                    "demo": {
                        "inflicted": 0,
                        "taken": 1
                    }
                }
            }
        ],
        "stats": {
            "ball": {
                "possession_time": 157.13,
                "time_in_side": 151.97
            },
            "core": {
                "shots": 13,
                "shots_against": 6,
                "goals": 2,
                "goals_against": 3,
                "saves": 1,
                "assists": 2,
                "score": 946,
                "shooting_percentage": 15.384615
            },
            "boost": {
                "bpm": 1245,
                "bcpm": 1263.612,
                "avg_amount": 135.63,
                "amount_collected": 7469,
                "amount_stolen": 2114,
                "amount_collected_big": 4756,
                "amount_stolen_big": 1028,
                "amount_collected_small": 2713,
                "amount_stolen_small": 1086,
                "count_collected_big": 61,
                "count_stolen_big": 13,
                "count_collected_small": 235,
                "count_stolen_small": 98,
                "amount_overfill": 1251,
                "amount_overfill_stolen": 289,
                "amount_used_while_supersonic": 1158,
                "time_zero_boost": 138.45,
                "time_full_boost": 120.11,
                "time_boost_0_25": 447.68002,
                "time_boost_25_50": 250.47,
                "time_boost_50_75": 179.74,
                "time_boost_75_100": 212.13
            },
            "movement": {
                "total_distance": 1660247,
                "time_supersonic_speed": 177.19,
                "time_boost_speed": 472.39,
                "time_slow_speed": 459.7,
                "time_ground": 617.27,
                "time_low_air": 427.02,
                "time_high_air": 64.979996,
                "time_powerslide": 20.25,
                "count_powerslide": 184
            },
            "positioning": {
                "time_defensive_third": 435.02,
                "time_neutral_third": 356.72,
                "time_offensive_third": 317.54,
                "time_defensive_half": 606.04004,
                "time_offensive_half": 503.24,
                "time_behind_ball": 819.88,
                "time_infront_ball": 289.41
            },
            "demo": {
                "inflicted": 2,
                "taken": 2
            }
        }
    },
    "playlist_name": "Private",
    "map_name": "DFH Stadium",
    "server": {
        "name": "RLCS007-Aurora",
        "region": "TR7"
    }
}